ansiconverter/__init__.py
ansiconverter/converter.py
ansiconverter/styles.py
test/test_ansiconverter.py
ansiconverter-2.0.0.dist-info/LICENSE.md
ansiconverter-2.0.0.dist-info/METADATA
ansiconverter-2.0.0.dist-info/WHEEL
ansiconverter-2.0.0.dist-info/top_level.txt
ansiconverter-2.0.0.dist-info/RECORD
