Metadata-Version: 2.1
Name: ansiconverter
Version: 2.0.0
Summary: Convert any colour, from RGB or hexadecimal format, to ANSI code.
Home-page: https://github.com/thomassamoth/ansiconverter
Author: Thomas Beyet
License: MIT
Project-URL: source, http://github.com/thomassamoth/ansiconverter
Classifier: Development Status :: 5 - Production/Stable
Classifier: Programming Language :: Python :: 3
Classifier: Programming Language :: Python :: 3.6
Classifier: Programming Language :: Python :: 3.7
Classifier: Programming Language :: Python :: 3.8
Classifier: Programming Language :: Python :: 3.9
Classifier: Programming Language :: Python :: 3.10
Classifier: Programming Language :: Python :: 3 :: Only
Classifier: License :: OSI Approved :: MIT License
Classifier: Operating System :: OS Independent
Requires-Python: >=3.6
License-File: LICENSE.md
Provides-Extra: dev
Requires-Dist: pytest >=3.6 ; extra == 'dev'
